isofate/__init__.py
isofate/atmodeller_coupler.py
isofate/constants.py
isofate/isofate_coupler.py
isofate/isofunks.py
isofate/isoplot.py
isofate/orbit_params.py
isofate/sim.py
isofate/test_Fxuv.py
isofate/test_isocalc.py
isofate/data/melt_fraction_grid.npz
isofate-0.1.2.dist-info/licenses/LICENSE
isofate-0.1.2.dist-info/METADATA
isofate-0.1.2.dist-info/WHEEL
isofate-0.1.2.dist-info/top_level.txt
isofate-0.1.2.dist-info/RECORD
