Metadata-Version: 2.4
Name: isofate
Version: 0.1.2
Requires-Python: >=3.11
License-File: LICENSE
Requires-Dist: numpy==2.3
Requires-Dist: scipy==1.16.1
Requires-Dist: matplotlib==3.10.0
Requires-Dist: atmodeller>=0.7.0
Requires-Dist: optimistix==0.0.10
Dynamic: license-file
